qgis_plugin_dev_tools/__init__.py
qgis_plugin_dev_tools/__main__.py
qgis_plugin_dev_tools/py.typed
qgis_plugin_dev_tools/build/__init__.py
qgis_plugin_dev_tools/build/changelog_parser.py
qgis_plugin_dev_tools/build/distribution.py
qgis_plugin_dev_tools/build/metadata.py
qgis_plugin_dev_tools/build/packaging.py
qgis_plugin_dev_tools/build/rewrite_imports.py
qgis_plugin_dev_tools/cli/__init__.py
qgis_plugin_dev_tools/config/__init__.py
qgis_plugin_dev_tools/config/dotenv.py
qgis_plugin_dev_tools/config/pyproject.py
qgis_plugin_dev_tools/publish/__init__.py
qgis_plugin_dev_tools/start/__init__.py
qgis_plugin_dev_tools/start/config.py
qgis_plugin_dev_tools/start/daemon_server.py
qgis_plugin_dev_tools/start/launch.py
qgis_plugin_dev_tools/start/bootstrap/__init__.py
qgis_plugin_dev_tools/start/bootstrap/template.py
qgis_plugin_dev_tools/utils/__init__.py
qgis_plugin_dev_tools/utils/distributions.py
qgis_plugin_dev_tools-0.9.1.dist-info/LICENSE
qgis_plugin_dev_tools-0.9.1.dist-info/METADATA
qgis_plugin_dev_tools-0.9.1.dist-info/WHEEL
qgis_plugin_dev_tools-0.9.1.dist-info/entry_points.txt
qgis_plugin_dev_tools-0.9.1.dist-info/top_level.txt
qgis_plugin_dev_tools-0.9.1.dist-info/RECORD
