Metadata-Version: 2.1
Name: qgis-plugin-dev-tools
Version: 0.9.1
Summary: QGIS plugin development and packaging tools, which make managing runtime dependencies easy.
Home-page: https://github.com/nlsfi/qgis-plugin-dev-tools
Author: National Land Survey of Finland
Author-email: os@nls.fi
License: GNU GPL v3.0
Project-URL: Changelog, https://github.com/nlsfi/qgis-plugin-dev-tools/blob/main/CHANGELOG.md
Keywords: qgis
Classifier: Development Status :: 3 - Alpha
Classifier: Intended Audience :: Developers
Classifier: License :: OSI Approved :: GNU General Public License v3 (GPLv3)
Classifier: Operating System :: OS Independent
Classifier: Programming Language :: Python :: 3
Classifier: Programming Language :: Python :: 3.9
Classifier: Programming Language :: Python :: 3.10
Classifier: Programming Language :: Python :: 3 :: Only
Classifier: Programming Language :: Python :: Implementation :: CPython
Classifier: Topic :: Software Development :: Build Tools
Classifier: Typing :: Typed
Requires-Python: >=3.9
License-File: LICENSE
Requires-Dist: packaging>=21.0
Requires-Dist: tomli>=2.0.0
Requires-Dist: python-dotenv>=0.19.0
Requires-Dist: importlib-metadata>=4.9.0
Requires-Dist: requests>=2.27.0
